ut_types/__init__.py
ut_types/beer.py
ut_types/brewery.py
ut_types/checkin.py
ut_types/injector.py
ut_types/menu.py
ut_types/other.py
ut_types/py.typed
ut_types/user.py
ut_types/venue.py
ut_types-0.1.0.dist-info/METADATA
ut_types-0.1.0.dist-info/WHEEL
ut_types-0.1.0.dist-info/RECORD
